{
  "updatedAt": "2026-07-04T04:00:57.427Z",
  "count": 4,
  "trends": [
    {
      "rank": 28,
      "query": "pitt jolie miraval lawsuit",
      "searchVolume": 20000,
      "startedAt": "",
      "endedAt": "",
      "active": true,
      "breakdown": [],
      "exploreUrl": "https://serpapi.com/search.json?data_type=TIMESERIES&date=now+1-d&engine=google_trends&geo=US&hl=en&q=pitt+jolie+miraval+lawsuit&tz=420",
      "increasePercentage": 1000,
      "source": "serpapi-google-trends",
      "text": "pitt jolie miraval lawsuit",
      "trendScore": 24,
      "detectedAt": "2026-07-04T04:00:54.756Z"
    },
    {
      "rank": 127,
      "query": "donald trump park signage lawsuit",
      "searchVolume": 10000,
      "startedAt": "",
      "endedAt": "",
      "active": false,
      "breakdown": [],
      "exploreUrl": "https://serpapi.com/search.json?data_type=TIMESERIES&date=now+1-d&engine=google_trends&geo=US&hl=en&q=donald+trump+park+signage+lawsuit&tz=420",
      "increasePercentage": 400,
      "source": "serpapi-google-trends",
      "text": "donald trump park signage lawsuit",
      "trendScore": 8,
      "detectedAt": "2026-07-04T04:00:54.756Z"
    },
    {
      "rank": 145,
      "query": "judge kenney philadelphia ice lawsuit",
      "searchVolume": 5000,
      "startedAt": "",
      "endedAt": "",
      "active": false,
      "breakdown": [],
      "exploreUrl": "https://serpapi.com/search.json?data_type=TIMESERIES&date=now+1-d&engine=google_trends&geo=US&hl=en&q=judge+kenney+philadelphia+ice+lawsuit&tz=420",
      "increasePercentage": 200,
      "source": "serpapi-google-trends",
      "text": "judge kenney philadelphia ice lawsuit",
      "trendScore": 8,
      "detectedAt": "2026-07-04T04:00:54.756Z"
    },
    {
      "rank": 223,
      "query": "winco fireworks recall",
      "searchVolume": 1000,
      "startedAt": "",
      "endedAt": "",
      "active": false,
      "breakdown": [],
      "exploreUrl": "https://serpapi.com/search.json?data_type=TIMESERIES&date=now+1-d&engine=google_trends&geo=US&hl=en&q=winco+fireworks+recall&tz=420",
      "increasePercentage": 200,
      "source": "serpapi-google-trends",
      "text": "winco fireworks recall",
      "trendScore": 8,
      "detectedAt": "2026-07-04T04:00:54.756Z"
    }
  ]
}
