{
  "updatedAt": "2026-07-10T14:50:49.895Z",
  "count": 8,
  "trends": [
    {
      "rank": 53,
      "query": "irs july 10 refund deadline",
      "searchVolume": 10000,
      "startedAt": "",
      "endedAt": "",
      "active": true,
      "breakdown": [
        "covid tax refund",
        "irs tax refund"
      ],
      "exploreUrl": "https://serpapi.com/search.json?data_type=TIMESERIES&date=now+1-d&engine=google_trends&geo=US&hl=en&q=irs+july+10+refund+deadline&tz=420",
      "increasePercentage": 300,
      "source": "serpapi-google-trends",
      "text": "irs july 10 refund deadline covid tax refund irs tax refund",
      "trendScore": 35,
      "detectedAt": "2026-07-10T14:50:36.403Z"
    },
    {
      "rank": 111,
      "query": "kia telluride fire recall",
      "searchVolume": 1000,
      "startedAt": "",
      "endedAt": "",
      "active": true,
      "breakdown": [
        "kia telluride fire risk recall"
      ],
      "exploreUrl": "https://serpapi.com/search.json?data_type=TIMESERIES&date=now+1-d&engine=google_trends&geo=US&hl=en&q=kia+telluride+fire+recall&tz=420",
      "increasePercentage": 100,
      "source": "serpapi-google-trends",
      "text": "kia telluride fire recall kia telluride fire risk recall",
      "trendScore": 25,
      "detectedAt": "2026-07-10T14:50:36.403Z"
    },
    {
      "rank": 15,
      "query": "lowe's kobalt yard tool recall",
      "searchVolume": 10000,
      "startedAt": "",
      "endedAt": "",
      "active": true,
      "breakdown": [],
      "exploreUrl": "https://serpapi.com/search.json?data_type=TIMESERIES&date=now+1-d&engine=google_trends&geo=US&hl=en&q=lowe%27s+kobalt+yard+tool+recall&tz=420",
      "increasePercentage": 400,
      "source": "serpapi-google-trends",
      "text": "lowe's kobalt yard tool recall",
      "trendScore": 23,
      "detectedAt": "2026-07-10T14:50:36.403Z"
    },
    {
      "rank": 56,
      "query": "target water beads lawsuit",
      "searchVolume": 5000,
      "startedAt": "",
      "endedAt": "",
      "active": true,
      "breakdown": [],
      "exploreUrl": "https://serpapi.com/search.json?data_type=TIMESERIES&date=now+1-d&engine=google_trends&geo=US&hl=en&q=target+water+beads+lawsuit&tz=420",
      "increasePercentage": 200,
      "source": "serpapi-google-trends",
      "text": "target water beads lawsuit",
      "trendScore": 23,
      "detectedAt": "2026-07-10T14:50:36.403Z"
    },
    {
      "rank": 288,
      "query": "prednisolone acetate ophthalmic suspension recall",
      "searchVolume": 2000,
      "startedAt": "",
      "endedAt": "",
      "active": false,
      "breakdown": [
        "eye drop recall july 2026",
        "eye drop recall",
        "eyedrop recall"
      ],
      "exploreUrl": "https://serpapi.com/search.json?data_type=TIMESERIES&date=now+1-d&engine=google_trends&geo=US&hl=en&q=prednisolone+acetate+ophthalmic+suspension+recall&tz=420",
      "increasePercentage": 50,
      "source": "serpapi-google-trends",
      "text": "prednisolone acetate ophthalmic suspension recall eye drop recall july 2026 eye drop recall eyedrop recall",
      "trendScore": 14,
      "detectedAt": "2026-07-10T14:50:36.403Z"
    },
    {
      "rank": 322,
      "query": "prince harry associated newspapers lawsuit",
      "searchVolume": 2000,
      "startedAt": "",
      "endedAt": "",
      "active": false,
      "breakdown": [
        "daily mail"
      ],
      "exploreUrl": "https://serpapi.com/search.json?data_type=TIMESERIES&date=now+1-d&engine=google_trends&geo=US&hl=en&q=prince+harry+associated+newspapers+lawsuit&tz=420",
      "increasePercentage": 50,
      "source": "serpapi-google-trends",
      "text": "prince harry associated newspapers lawsuit daily mail",
      "trendScore": 10,
      "detectedAt": "2026-07-10T14:50:36.403Z"
    },
    {
      "rank": 144,
      "query": "bts swim hybe copyright lawsuit",
      "searchVolume": 5000,
      "startedAt": "",
      "endedAt": "",
      "active": false,
      "breakdown": [],
      "exploreUrl": "https://serpapi.com/search.json?data_type=TIMESERIES&date=now+1-d&engine=google_trends&geo=US&hl=en&q=bts+swim+hybe+copyright+lawsuit&tz=420",
      "increasePercentage": 100,
      "source": "serpapi-google-trends",
      "text": "bts swim hybe copyright lawsuit",
      "trendScore": 8,
      "detectedAt": "2026-07-10T14:50:36.403Z"
    },
    {
      "rank": 209,
      "query": "iphone siri delayed launch lawsuit",
      "searchVolume": 2000,
      "startedAt": "",
      "endedAt": "",
      "active": false,
      "breakdown": [],
      "exploreUrl": "https://serpapi.com/search.json?data_type=TIMESERIES&date=now+1-d&engine=google_trends&geo=US&hl=en&q=iphone+siri+delayed+launch+lawsuit&tz=420",
      "increasePercentage": 75,
      "source": "serpapi-google-trends",
      "text": "iphone siri delayed launch lawsuit",
      "trendScore": 8,
      "detectedAt": "2026-07-10T14:50:36.403Z"
    }
  ]
}
