[
  {
    "rank": 16,
    "query": "supreme court",
    "searchVolume": 20000,
    "startedAt": "",
    "endedAt": "",
    "active": true,
    "breakdown": [
      "lawsuit"
    ],
    "exploreUrl": "https://serpapi.com/search.json?data_type=TIMESERIES&date=now+1-d&engine=google_trends&geo=US&hl=en&q=supreme+court&tz=420",
    "increasePercentage": 1000,
    "source": "serpapi-google-trends",
    "text": "supreme court lawsuit",
    "trendScore": 26,
    "detectedAt": "2026-05-26T20:25:06.994Z"
  },
  {
    "rank": 1,
    "query": "walmart blackstone parmesan ranch recall",
    "searchVolume": 20000,
    "startedAt": "",
    "endedAt": "",
    "active": true,
    "breakdown": [],
    "exploreUrl": "https://serpapi.com/search.json?data_type=TIMESERIES&date=now+1-d&engine=google_trends&geo=US&hl=en&q=walmart+blackstone+parmesan+ranch+recall&tz=420",
    "increasePercentage": 1000,
    "source": "serpapi-google-trends",
    "text": "walmart blackstone parmesan ranch recall",
    "trendScore": 24,
    "detectedAt": "2026-05-26T20:25:06.994Z"
  },
  {
    "rank": 90,
    "query": "carnival cruise hot deck lawsuit",
    "searchVolume": 500,
    "startedAt": "",
    "endedAt": "",
    "active": true,
    "breakdown": [],
    "exploreUrl": "https://serpapi.com/search.json?data_type=TIMESERIES&date=now+1-d&engine=google_trends&geo=US&hl=en&q=carnival+cruise+hot+deck+lawsuit&tz=420",
    "increasePercentage": 100,
    "source": "serpapi-google-trends",
    "text": "carnival cruise hot deck lawsuit",
    "trendScore": 23,
    "detectedAt": "2026-05-26T20:25:06.994Z"
  },
  {
    "rank": 135,
    "query": "sks copack beverage recall",
    "searchVolume": 5000,
    "startedAt": "",
    "endedAt": "",
    "active": false,
    "breakdown": [],
    "exploreUrl": "https://serpapi.com/search.json?data_type=TIMESERIES&date=now+1-d&engine=google_trends&geo=US&hl=en&q=sks+copack+beverage+recall&tz=420",
    "increasePercentage": 50,
    "source": "serpapi-google-trends",
    "text": "sks copack beverage recall",
    "trendScore": 8,
    "detectedAt": "2026-05-26T20:25:06.994Z"
  },
  {
    "rank": 409,
    "query": "hyundai vehicle recall software bug",
    "searchVolume": 200,
    "startedAt": "",
    "endedAt": "",
    "active": false,
    "breakdown": [],
    "exploreUrl": "https://serpapi.com/search.json?data_type=TIMESERIES&date=now+1-d&engine=google_trends&geo=US&hl=en&q=hyundai+vehicle+recall+software+bug&tz=420",
    "increasePercentage": 50,
    "source": "serpapi-google-trends",
    "text": "hyundai vehicle recall software bug",
    "trendScore": 8,
    "detectedAt": "2026-05-26T20:25:06.994Z"
  }
]
