{
  "updatedAt": "2026-07-19T13:52:46.992Z",
  "item": {
    "id": "avanos-medical-inc-brand-name-corflo-product-name-corflo-safety-peg-kit-model-catalog-numb",
    "slug": "avanos-medical-inc-brand-name-corflo-product-name-corflo-safety-peg-kit-model-catalog-numb",
    "title": "Avanos Medical, Inc.: Brand Name: CORFLO Product Name: CORFLO Safety PEG Kit Model/Catalog Number: 30-5320 Recall",
    "type": "recall",
    "status": "active",
    "company": "Avanos Medical, Inc.",
    "brand": "Avanos Medical, Inc.",
    "product": "Brand Name: CORFLO Product Name: CORFLO Safety PEG Kit Model/Catalog Number: 30-5320",
    "category": "Recall",
    "summary": "Lidocaine hydrochloride injection, the subject of a supplier recall for quality issues, were included into sterile kits and sets. Product details: Brand Name: CORFLO Product Name: CORFLO Safety PEG Kit Model/Catalog Number: 30-5320",
    "affectedPeople": "US Nationwide distribution.",
    "remedy": "Affected quantity: 61 kits",
    "payoutAmount": "Refund, replacement, correction, or disposal if stated by the official notice",
    "deadline": null,
    "officialClaimUrl": "",
    "officialSourceUrl": "https://api.fda.gov/device/enforcement.json?sort=report_date:desc&limit=15",
    "sourceAgency": "FDA",
    "searchVolume": "",
    "trendScore": 0,
    "matchedQueries": [],
    "officialVerified": true,
    "officialRecordId": "Z-2334-2026",
    "recallInitiationDate": "20260430",
    "lastUpdated": "2026-06-29T20:15:35.065Z",
    "url": "https://simon622.shop/item/avanos-medical-inc-brand-name-corflo-product-name-corflo-safety-peg-kit-model-catalog-numb/"
  }
}
