{
  "updatedAt": "2026-07-19T08:32:21.460Z",
  "item": {
    "id": "taylor-farms-recall",
    "slug": "taylor-farms-recall",
    "title": "Taylor Farms Recall: Consumer Alert Monitoring",
    "type": "recall",
    "status": "monitoring",
    "company": "",
    "brand": "",
    "product": "taylor farms recall",
    "category": "Recall monitoring",
    "summary": "This page was surfaced from current search trends and is held in monitoring status until a matching official source is verified.",
    "affectedPeople": "Consumers searching for this alert should confirm details through official sources.",
    "remedy": "No consumer action is recommended until an official source is attached.",
    "payoutAmount": "Not verified",
    "deadline": null,
    "officialClaimUrl": "",
    "officialSourceUrl": "",
    "thirdPartySourceUrl": "",
    "trendExploreUrl": "https://serpapi.com/search.json?data_type=TIMESERIES&date=now+1-d&engine=google_trends&geo=US&hl=en&q=taylor+farms+recall&tz=420",
    "sourceAgency": "COMPANY",
    "sourceConfidence": "trend-only",
    "searchVolume": 5000,
    "trendScore": 20,
    "matchedQueries": [
      "taylor farms recall",
      "salad",
      "bill marler cyclospora lawsuit"
    ],
    "officialVerified": false,
    "lastUpdated": "2026-07-19T08:32:13.598Z",
    "url": "https://simon622.shop/item/taylor-farms-recall/"
  }
}
